{
    "USA": {
        "beans": {
            "Mexico": { "cost": 5, "impact": 55, "longitude": -102.5528, "latitude": 23.6345 },
            "USA": { "cost": 6, "impact": 62, "longitude": -95.7129, "latitude": 37.0902 }
        },
        "rice": {
            "USA": { "cost": 4, "impact": 48, "longitude": -95.7129, "latitude": 37.0902 },
            "China": { "cost": 3, "impact": 50, "longitude": 104.1954, "latitude": 35.8617 }
        },
        "meat": {
            "Brazil": { "cost": 9, "impact": 130, "longitude": -51.9253, "latitude": -14.2350 },
            "USA": { "cost": 12, "impact": 140, "longitude": -95.7129, "latitude": 37.0902 }
        },
        "vegetables": {
            "USA": { "cost": 3, "impact": 36, "longitude": -95.7129, "latitude": 37.0902 },
            "Mexico": { "cost": 4, "impact": 34, "longitude": -102.5528, "latitude": 23.6345 }
        },
        "cheese": {
            "USA": { "cost": 8, "impact": 95, "longitude": -95.7129, "latitude": 37.0902 },
            "France": { "cost": 10, "impact": 90, "longitude": 2.2137, "latitude": 46.6034 }
        },
        "tortillas": {
            "Mexico": { "cost": 2, "impact": 29, "longitude": -102.5528, "latitude": 23.6345 },
            "USA": { "cost": 3, "impact": 33, "longitude": -95.7129, "latitude": 37.0902 }
        }
    },
    "China": {
        "beans": {
            "Mexico": { "cost": 5, "impact": 55, "longitude": -102.5528, "latitude": 23.6345 },
            "China": { "cost": 4, "impact": 51, "longitude": 104.1954, "latitude": 35.8617 }
        },
        "rice": {
            "China": { "cost": 3, "impact": 50, "longitude": 104.1954, "latitude": 35.8617 },
            "USA": { "cost": 4, "impact": 48, "longitude": -95.7129, "latitude": 37.0902 }
        },
        "meat": {
            "Brazil": { "cost": 9, "impact": 130, "longitude": -51.9253, "latitude": -14.2350 },
            "USA": { "cost": 12, "impact": 140, "longitude": -95.7129, "latitude": 37.0902 }
        },
        "vegetables": {
            "USA": { "cost": 3, "impact": 36, "longitude": -95.7129, "latitude": 37.0902 },
            "Mexico": { "cost": 4, "impact": 34, "longitude": -102.5528, "latitude": 23.6345 }
        },
        "cheese": {
            "USA": { "cost": 8, "impact": 95, "longitude": -95.7129, "latitude": 37.0902 },
            "France": { "cost": 10, "impact": 90, "longitude": 2.2137, "latitude": 46.6034 }
        },
        "tortillas": {
            "Mexico": { "cost": 2, "impact": 29, "longitude": -102.5528, "latitude": 23.6345 },
            "USA": { "cost": 3, "impact": 33, "longitude": -95.7129, "latitude": 37.0902 }
        }
    },
    "Brazil": {
        "beans": {
            "USA": { "cost": 6, "impact": 62, "longitude": -95.7129, "latitude": 37.0902 },
            "Brazil": { "cost": 5, "impact": 55, "longitude": -51.9253, "latitude": -14.2350 }
        },
        "rice": {
            "Brazil": { "cost": 3, "impact": 50, "longitude": -51.9253, "latitude": -14.2350 },
            "USA": { "cost": 4, "impact": 48, "longitude": -95.7129, "latitude": 37.0902 }
        },
        "meat": {
            "Brazil": { "cost": 9, "impact": 130, "longitude": -51.9253, "latitude": -14.2350 },
            "USA": { "cost": 12, "impact": 140, "longitude": -95.7129, "latitude": 37.0902 }
        },
        "vegetables": {
            "USA": { "cost": 3, "impact": 36, "longitude": -95.7129, "latitude": 37.0902 },
            "Mexico": { "cost": 4, "impact": 34, "longitude": -102.5528, "latitude": 23.6345 }
        },
        "cheese": {
            "USA": { "cost": 8, "impact": 95, "longitude": -95.7129, "latitude": 37.0902 },
            "France": { "cost": 10, "impact": 90, "longitude": 2.2137, "latitude": 46.6034 }
        },
        "tortillas": {
            "Mexico": { "cost": 2, "impact": 29, "longitude": -102.5528, "latitude": 23.6345 },
            "USA": { "cost": 3, "impact": 33, "longitude": -95.7129, "latitude": 37.0902 }
        }
    }
}